[
  {
    "name": "Hoshikawa",
    "imgUrl": "/img/t_hoshikawa_color_350-300x300.jpg"
  },
  {
    "name": "Haley",
    "imgUrl": "/img/haley_koike.jpg"
  },
  {
    "name": "Nicolas Cage",
    "imgUrl": "https://www.placecage.com/300/300"
  },
  {
    "name": "Nicolas Cage",
    "imgUrl": "https://www.placecage.com/301/301"
  },
  {
    "name": "Nicolas Cage",
    "imgUrl": "https://www.placecage.com/302/302"
  },
  {
    "name": "Nicolas Cage",
    "imgUrl": "https://www.placecage.com/303/303"
  },
  {
    "name": "Nicolas Cage",
    "imgUrl": "https://www.placecage.com/304/304"
  },
  {
    "name": "Nicolas Cage",
    "imgUrl": "https://www.placecage.com/305/305"
  }
]
